s3file/__init__.py
s3file/main.py
techtrash_s3file-0.1.0.dist-info/METADATA
techtrash_s3file-0.1.0.dist-info/WHEEL
techtrash_s3file-0.1.0.dist-info/licenses/LICENSE
techtrash_s3file-0.1.0.dist-info/RECORD
